setup.py
classifier/__init__.py
classifier/classifier.py
classifier.egg-info/PKG-INFO
classifier.egg-info/SOURCES.txt
classifier.egg-info/dependency_links.txt
classifier.egg-info/entry_points.txt
classifier.egg-info/not-zip-safe
classifier.egg-info/requires.txt
classifier.egg-info/top_level.txt