Metadata-Version: 1.0
Name: classifier
Version: 1.6
Summary: Classify the files in your Downloads folder into suitable destinations.
Home-page: http://github.com/bhrigu123/classifier
Author: Bhrigu Srivastava
Author-email: captain.bhrigu@gmail.com
License: MIT
Platform: UNKNOWN
